LICENSE
MANIFEST.in
README.md
package.json
setup.py
dash_oflog_components/DualInput.py
dash_oflog_components/DualInput2.py
dash_oflog_components/MultiSelect.py
dash_oflog_components/RadioButton.py
dash_oflog_components/Test.py
dash_oflog_components/Test2.py
dash_oflog_components/__init__.py
dash_oflog_components/_imports_.py
dash_oflog_components/dash_oflog_components.min.js
dash_oflog_components/dash_oflog_components.min.js.map
dash_oflog_components/metadata.json
dash_oflog_components/package-info.json
dash_oflog_components.egg-info/PKG-INFO
dash_oflog_components.egg-info/SOURCES.txt
dash_oflog_components.egg-info/dependency_links.txt
dash_oflog_components.egg-info/top_level.txt
tests/test_usage.py