Metadata-Version: 2.1
Name: dash-oflog-components
Version: 0.0.50
Summary: Dash react components for use in oflog data products
Author: Haydn Jenkins <haydn.jenkins@levellingup.gov.uk>
License: MIT
Classifier: Framework :: Dash
License-File: LICENSE
